LICENSE
README.md
setup.py
src/tag_version.egg-info/PKG-INFO
src/tag_version.egg-info/SOURCES.txt
src/tag_version.egg-info/dependency_links.txt
src/tag_version.egg-info/entry_points.txt
src/tag_version.egg-info/requires.txt
src/tag_version.egg-info/top_level.txt
src/tagversion/__init__.py
src/tagversion/argparse.py
src/tagversion/entrypoints.py
src/tagversion/exceptions.py
src/tagversion/git.py
src/tagversion/version.py
src/tagversion/write.py