Metadata-Version: 2.1
Name: tag-version
Version: 0.1.3
Summary: semantic versioned git tags
Home-page: https://github.com/openslate/tag-version
Author: DoubleVerify
Author-email: code@doubleverify.com
License: UNKNOWN
Platform: UNKNOWN
License-File: LICENSE
